{"ocrText":"对于本院调取的证据，被告虽有异议，但未提供反驳证据，且被告之父赵锦堂对于天津市国土资源和房屋管理局的上述变更登记行为已提起行政诉讼，并已有本院生效裁定，故对于被告所持异议，本院不予采纳，本院对该组证据予以采信。对于原、被告提交的上述证据，对方当事人对真实性均未持异议，本院对真实性均予以认定。原告提交的（2012）红民初字第1118号民事判决书及该案承办人至涉诉房屋的现场勘查笔录及现场绘制平面图能够证实原、被告发生争议的涉诉房屋为同一标的，涉诉房屋实际门牌号码为红桥区大新街62号增1号，位于门牌号为大新街62号与大新街64号之间，本案审理中，承办人亦曾于2017年2月21日至涉诉房屋现场勘查，并制作现场勘查笔录；（2015）红行初字第0044号行政诉讼的现场勘查笔录中，天津市衬衣总厂确认红桥区西于庄大街15号与大新街62号增1号系同一处房屋；本院调取的证据能够证实天津市国土资源和房屋管理局根据天津市衬衣总厂的申请将不动产登记簿上记载的红桥区西于庄大街15号更正为红桥区西于庄大新街89号；在红桥区西于庄大街15号房屋的不动产登记簿与红桥区西于庄大新街89号的不动产权证书以及原告与第三人于1988年和2016年就涉诉房屋地址更正前后两次签订的租赁合同中，其上所载明的房屋建筑面积一致，均为58．5平方米；综上，上述证据形成完整的证据链，能够证实天津市红桥区西于庄大新街89号即为原、被告争议之门牌号码为天津市红桥区大新街62号增1号之房屋。根据《中华人民共和国物权法》第十七条之规定，11","pdfURL":"http://130.10.0.165:8019/api/File/GetPDF?Name=4ae6bb0154fc4e53ace24593e67a2cd8.pdf","textResult":[{"charNum":"24","isHandwritten":"false","leftBottom":"197, 217","leftTop":"197, 182","rightBottom":"963, 217","rightTop":"963, 182","text":"对于本院调取的证据，被告虽有异议，但未提供反驳证"},{"charNum":"26","isHandwritten":"false","leftBottom":"136, 267","leftTop":"136, 231","rightBottom":"963, 268","rightTop":"963, 233","text":"据，且被告之父赵锦堂对于天津市国土资源和房屋管理局的"},{"charNum":"26","isHandwritten":"false","leftBottom":"140, 318","leftTop":"140, 283","rightBottom":"952, 320","rightTop":"952, 285","text":"上述变更登记行为已提起行政诉讼，并已有本院生效裁定，"},{"charNum":"26","isHandwritten":"false","leftBottom":"128, 369","leftTop":"128, 333","rightBottom":"965, 370","rightTop":"965, 334","text":"故对于被告所持异议，本院不予采纳，本院对该组证据予以"},{"charNum":"3","isHandwritten":"false","leftBottom":"134, 416","leftTop":"134, 383","rightBottom":"217, 417","rightTop":"217, 384","text":"采信。"},{"charNum":"24","isHandwritten":"false","leftBottom":"194, 470","leftTop":"194, 435","rightBottom":"962, 472","rightTop":"963, 437","text":"对于原、被告提交的上述证据，对方当事人对真实性均"},{"charNum":"28","isHandwritten":"false","leftBottom":"134, 520","leftTop":"134, 484","rightBottom":"962, 522","rightTop":"962, 486","text":"未持异议，本院对真实性均予以认定。原告提交的（2012）"},{"charNum":"27","isHandwritten":"false","leftBottom":"133, 569","leftTop":"133, 534","rightBottom":"961, 572","rightTop":"961, 536","text":"红民初字第1118号民事判决书及该案承办人至涉诉房屋的"},{"charNum":"26","isHandwritten":"false","leftBottom":"130, 620","leftTop":"130, 586","rightBottom":"964, 623","rightTop":"964, 589","text":"现场勘查笔录及现场绘制平面图能够证实原、被告发生争议"},{"charNum":"26","isHandwritten":"false","leftBottom":"130, 671","leftTop":"130, 635","rightBottom":"964, 673","rightTop":"964, 637","text":"的涉诉房屋为同一标的，涉诉房屋实际门牌号码为红桥区大"},{"charNum":"29","isHandwritten":"false","leftBottom":"128, 720","leftTop":"128, 686","rightBottom":"964, 721","rightTop":"964, 687","text":"新街62号增1号，位于门牌号为大新街62号与大新街64号之"},{"charNum":"29","isHandwritten":"false","leftBottom":"128, 770","leftTop":"128, 735","rightBottom":"961, 771","rightTop":"961, 737","text":"间，本案审理中，承办人亦曾于2017年2月21日至涉诉房屋"},{"charNum":"30","isHandwritten":"false","leftBottom":"128, 820","leftTop":"128, 784","rightBottom":"964, 822","rightTop":"965, 786","text":"现场勘查，并制作现场勘查笔录；（2015）红行初字第0044"},{"charNum":"26","isHandwritten":"false","leftBottom":"132, 870","leftTop":"132, 835","rightBottom":"960, 871","rightTop":"960, 836","text":"号行政诉讼的现场勘查笔录中，天津市衬衣总厂确认红桥区"},{"charNum":"28","isHandwritten":"false","leftBottom":"128, 920","leftTop":"128, 884","rightBottom":"962, 921","rightTop":"962, 886","text":"西于庄大街15号与大新街62号增1号系同一处房屋；本院调"},{"charNum":"25","isHandwritten":"false","leftBottom":"128, 970","leftTop":"128, 934","rightBottom":"960, 970","rightTop":"960, 934","text":"取的证据能够证实天津市国土资源和房屋管理局根据天津"},{"charNum":"25","isHandwritten":"false","leftBottom":"133, 1019","leftTop":"133, 983","rightBottom":"960, 1020","rightTop":"960, 983","text":"市衬衣总厂的申请将不动产登记簿上记载的红桥区西于庄"},{"charNum":"28","isHandwritten":"false","leftBottom":"132, 1069","leftTop":"132, 1034","rightBottom":"960, 1071","rightTop":"960, 1036","text":"大街15号更正为红桥区西于庄大新街89号；在红桥区西于庄"},{"charNum":"27","isHandwritten":"false","leftBottom":"134, 1119","leftTop":"134, 1084","rightBottom":"959, 1120","rightTop":"959, 1085","text":"大街15号房屋的不动产登记簿与红桥区西于庄大新街89号"},{"charNum":"29","isHandwritten":"false","leftBottom":"128, 1169","leftTop":"128, 1134","rightBottom":"961, 1169","rightTop":"961, 1134","text":"的不动产权证书以及原告与第三人于1988年和2016年就涉"},{"charNum":"26","isHandwritten":"false","leftBottom":"128, 1219","leftTop":"128, 1184","rightBottom":"962, 1219","rightTop":"962, 1184","text":"诉房屋地址更正前后两次签订的租赁合同中，其上所载明的"},{"charNum":"28","isHandwritten":"false","leftBottom":"132, 1270","leftTop":"132, 1235","rightBottom":"961, 1270","rightTop":"961, 1235","text":"房屋建筑面积一致，均为58．5平方米；综上，上述证据形成"},{"charNum":"27","isHandwritten":"false","leftBottom":"129, 1319","leftTop":"129, 1284","rightBottom":"960, 1319","rightTop":"960, 1284","text":"完整的证据链，能够证实天津市红桥区西于庄大新街89号即"},{"charNum":"27","isHandwritten":"false","leftBottom":"133, 1369","leftTop":"133, 1334","rightBottom":"963, 1369","rightTop":"963, 1334","text":"为原、被告争议之门牌号码为天津市红桥区大新街62号增1"},{"charNum":"27","isHandwritten":"false","leftBottom":"133, 1418","leftTop":"133, 1383","rightBottom":"961, 1418","rightTop":"961, 1382","text":"号之房屋。根据《中华人民共和国物权法》第十七条之规定，"},{"charNum":"2","isHandwritten":"false","leftBottom":"539, 1496","leftTop":"539, 1477","rightBottom":"558, 1496","rightTop":"558, 1477","text":"11"}]}