{"ocrText":"扣押、冻结其他等值财产。案件申请费5000元，由中民国际融资租赁股份有限公司负担。本裁定立即开始执行。如不服本裁定，可以自收到裁定书之日起五日内向本院申请复议一次。复议期间不停止裁定的执行。申请人在人民法院采取保全措施后三十日内不依法提起诉讼或者申请仲裁的，本院将依法解除保全。审判长案审判员民振代理审判员韩涛韩涛0一九年一月三日书记员耿小军","pdfURL":"http://130.10.0.165:8019/api/File/GetPDF?Name=30eb1160843c40cd88bed720b39d42bb.pdf","textResult":[{"charNum":"29","isHandwritten":"false","leftBottom":"161, 215","leftTop":"161, 180","rightBottom":"991, 217","rightTop":"991, 183","text":"扣押、冻结其他等值财产。案件申请费5000元，由中民国际融"},{"charNum":"12","isHandwritten":"false","leftBottom":"160, 266","leftTop":"160, 232","rightBottom":"509, 266","rightTop":"509, 232","text":"资租赁股份有限公司负担。"},{"charNum":"10","isHandwritten":"false","leftBottom":"217, 319","leftTop":"217, 285","rightBottom":"510, 319","rightTop":"510, 285","text":"本裁定立即开始执行。"},{"charNum":"25","isHandwritten":"false","leftBottom":"216, 370","leftTop":"217, 335","rightBottom":"985, 371","rightTop":"985, 337","text":"如不服本裁定，可以自收到裁定书之日起五日内向本院申"},{"charNum":"19","isHandwritten":"false","leftBottom":"161, 422","leftTop":"161, 388","rightBottom":"723, 423","rightTop":"723, 389","text":"请复议一次。复议期间不停止裁定的执行。"},{"charNum":"25","isHandwritten":"false","leftBottom":"221, 473","leftTop":"221, 439","rightBottom":"991, 474","rightTop":"991, 440","text":"申请人在人民法院采取保全措施后三十日内不依法提起诉"},{"charNum":"19","isHandwritten":"false","leftBottom":"161, 526","leftTop":"161, 492","rightBottom":"720, 526","rightTop":"720, 493","text":"讼或者申请仲裁的，本院将依法解除保全。"},{"charNum":"3","isHandwritten":"false","leftBottom":"681, 576","leftTop":"681, 543","rightBottom":"842, 577","rightTop":"842, 544","text":"审判长"},{"charNum":"1","isHandwritten":"true","leftBottom":"894, 581","leftTop":"894, 534","rightBottom":"935, 581","rightTop":"935, 534","text":"案"},{"charNum":"2","isHandwritten":"false","leftBottom":"684, 627","leftTop":"684, 595","rightBottom":"805, 627","rightTop":"806, 596","text":"审判"},{"charNum":"1","isHandwritten":"false","leftBottom":"797, 629","leftTop":"797, 596","rightBottom":"839, 629","rightTop":"839, 596","text":"员"},{"charNum":"2","isHandwritten":"true","leftBottom":"897, 637","leftTop":"897, 587","rightBottom":"1018, 637","rightTop":"1018, 587","text":"民振"},{"charNum":"5","isHandwritten":"false","leftBottom":"686, 680","leftTop":"686, 647","rightBottom":"840, 680","rightTop":"840, 647","text":"代理审判员"},{"charNum":"2","isHandwritten":"false","leftBottom":"894, 680","leftTop":"894, 647","rightBottom":"989, 680","rightTop":"989, 647","text":"韩涛"},{"charNum":"2","isHandwritten":"true","leftBottom":"992, 703","leftTop":"992, 636","rightBottom":"1079, 703","rightTop":"1079, 636","text":"韩涛"},{"charNum":"8","isHandwritten":"false","leftBottom":"724, 786","leftTop":"724, 750","rightBottom":"989, 786","rightTop":"989, 750","text":"0一九年一月三日"},{"charNum":"3","isHandwritten":"false","leftBottom":"685, 887","leftTop":"685, 854","rightBottom":"841, 888","rightTop":"841, 855","text":"书记员"},{"charNum":"3","isHandwritten":"false","leftBottom":"891, 888","leftTop":"891, 855","rightBottom":"987, 888","rightTop":"987, 855","text":"耿小军"}]}